[{"mid_date":"2021-09-20","norm_coh":0.8626,"smoothed":0.6689,"months_post_fire":-3.32},{"mid_date":"2021-10-02","norm_coh":0.7871,"smoothed":0.6714,"months_post_fire":-2.92},{"mid_date":"2021-10-14","norm_coh":0.6545,"smoothed":0.621,"months_post_fire":-2.53},{"mid_date":"2021-10-26","norm_coh":0.9072,"smoothed":0.7273,"months_post_fire":-2.14},{"mid_date":"2021-11-07","norm_coh":0.8925,"smoothed":0.707,"months_post_fire":-1.74},{"mid_date":"2021-11-19","norm_coh":0.8187,"smoothed":0.8048,"months_post_fire":-1.35},{"mid_date":"2021-12-01","norm_coh":0.9946,"smoothed":0.743,"months_post_fire":-0.95},{"mid_date":"2021-12-13","norm_coh":0.6233,"smoothed":0.756,"months_post_fire":-0.56},{"mid_date":"2021-12-25","norm_coh":0.7523,"smoothed":0.82,"months_post_fire":-0.16},{"mid_date":"2022-01-06","norm_coh":0.4848,"smoothed":0.6928,"months_post_fire":0.23},{"mid_date":"2022-01-18","norm_coh":1.075,"smoothed":0.898,"months_post_fire":0.62},{"mid_date":"2022-01-30","norm_coh":0.1833,"smoothed":0.5379,"months_post_fire":1.02},{"mid_date":"2022-02-11","norm_coh":1.5721,"smoothed":1.0686,"months_post_fire":1.41},{"mid_date":"2022-02-23","norm_coh":1.062,"smoothed":0.8728,"months_post_fire":1.81},{"mid_date":"2022-03-07","norm_coh":0.4988,"smoothed":0.6137,"months_post_fire":2.2},{"mid_date":"2022-03-19","norm_coh":0.4948,"smoothed":0.601,"months_post_fire":2.6},{"mid_date":"2022-03-31","norm_coh":0.8176,"smoothed":0.7354,"months_post_fire":2.99},{"mid_date":"2022-04-12","norm_coh":0.7656,"smoothed":0.7191,"months_post_fire":3.38},{"mid_date":"2022-04-24","norm_coh":0.5234,"smoothed":0.5651,"months_post_fire":3.78},{"mid_date":"2022-05-06","norm_coh":0.332,"smoothed":0.5165,"months_post_fire":4.17},{"mid_date":"2022-05-18","norm_coh":0.3596,"smoothed":0.5314,"months_post_fire":4.57},{"mid_date":"2022-05-30","norm_coh":0.7937,"smoothed":0.5411,"months_post_fire":4.96},{"mid_date":"2022-06-11","norm_coh":0.4012,"smoothed":0.5122,"months_post_fire":5.35},{"mid_date":"2022-06-23","norm_coh":0.1671,"smoothed":0.5117,"months_post_fire":5.75},{"mid_date":"2022-07-05","norm_coh":0.5276,"smoothed":0.5255,"months_post_fire":6.14},{"mid_date":"2022-07-17","norm_coh":0.6629,"smoothed":0.5363,"months_post_fire":6.54},{"mid_date":"2022-07-29","norm_coh":0.6013,"smoothed":0.5578,"months_post_fire":6.93},{"mid_date":"2022-08-10","norm_coh":0.5001,"smoothed":0.5333,"months_post_fire":7.33},{"mid_date":"2022-08-22","norm_coh":0.7601,"smoothed":0.5961,"months_post_fire":7.72},{"mid_date":"2022-09-03","norm_coh":0.6751,"smoothed":0.6704,"months_post_fire":8.11},{"mid_date":"2022-09-15","norm_coh":0.4511,"smoothed":0.6637,"months_post_fire":8.51},{"mid_date":"2022-09-27","norm_coh":0.5951,"smoothed":0.6829,"months_post_fire":8.9},{"mid_date":"2022-10-15","norm_coh":0.5248,"smoothed":0.7101,"months_post_fire":9.49},{"mid_date":"2022-11-02","norm_coh":1.0923,"smoothed":0.8447,"months_post_fire":10.09},{"mid_date":"2022-11-14","norm_coh":0.9843,"smoothed":0.8474,"months_post_fire":10.48},{"mid_date":"2022-11-26","norm_coh":0.454,"smoothed":0.7855,"months_post_fire":10.87},{"mid_date":"2022-12-08","norm_coh":0.8736,"smoothed":0.8816,"months_post_fire":11.27},{"mid_date":"2022-12-26","norm_coh":0.9008,"smoothed":0.8934,"months_post_fire":11.86},{"mid_date":"2023-01-13","norm_coh":1.5172,"smoothed":0.933,"months_post_fire":12.45},{"mid_date":"2023-01-31","norm_coh":0.9629,"smoothed":0.9185,"months_post_fire":13.04},{"mid_date":"2023-02-18","norm_coh":0.9137,"smoothed":0.8838,"months_post_fire":13.63},{"mid_date":"2023-03-02","norm_coh":0.8783,"smoothed":0.8959,"months_post_fire":14.03},{"mid_date":"2023-03-14","norm_coh":0.7249,"smoothed":0.89,"months_post_fire":14.42},{"mid_date":"2023-03-26","norm_coh":0.9614,"smoothed":0.8464,"months_post_fire":14.82},{"mid_date":"2023-04-07","norm_coh":0.9318,"smoothed":0.801,"months_post_fire":15.21},{"mid_date":"2023-04-19","norm_coh":0.6034,"smoothed":0.8041,"months_post_fire":15.6},{"mid_date":"2023-05-01","norm_coh":0.5873,"smoothed":0.8099,"months_post_fire":16.0},{"mid_date":"2023-05-13","norm_coh":0.8085,"smoothed":0.7907,"months_post_fire":16.39},{"mid_date":"2023-05-25","norm_coh":0.4213,"smoothed":0.745,"months_post_fire":16.79},{"mid_date":"2023-06-06","norm_coh":1.0172,"smoothed":0.7146,"months_post_fire":17.18},{"mid_date":"2023-06-18","norm_coh":0.9977,"smoothed":0.6709,"months_post_fire":17.58},{"mid_date":"2023-06-30","norm_coh":0.9769,"smoothed":0.6414,"months_post_fire":17.97},{"mid_date":"2023-07-12","norm_coh":0.6677,"smoothed":0.6185,"months_post_fire":18.36},{"mid_date":"2023-07-24","norm_coh":0.2215,"smoothed":0.56,"months_post_fire":18.76},{"mid_date":"2023-08-05","norm_coh":0.6269,"smoothed":0.5799,"months_post_fire":19.15},{"mid_date":"2023-08-17","norm_coh":0.4512,"smoothed":0.5428,"months_post_fire":19.55},{"mid_date":"2023-08-29","norm_coh":0.2794,"smoothed":0.5078,"months_post_fire":19.94},{"mid_date":"2023-09-10","norm_coh":0.3227,"smoothed":0.4675,"months_post_fire":20.34},{"mid_date":"2023-09-22","norm_coh":0.343,"smoothed":0.4504,"months_post_fire":20.73},{"mid_date":"2023-10-04","norm_coh":0.4579,"smoothed":0.5364,"months_post_fire":21.12},{"mid_date":"2023-10-16","norm_coh":0.6261,"smoothed":0.587,"months_post_fire":21.52},{"mid_date":"2023-10-28","norm_coh":0.6123,"smoothed":0.6218,"months_post_fire":21.91},{"mid_date":"2023-11-09","norm_coh":0.5337,"smoothed":0.6727,"months_post_fire":22.31},{"mid_date":"2023-11-21","norm_coh":0.4792,"smoothed":0.6518,"months_post_fire":22.7},{"mid_date":"2023-12-03","norm_coh":1.1685,"smoothed":0.6864,"months_post_fire":23.09},{"mid_date":"2023-12-15","norm_coh":1.154,"smoothed":0.698,"months_post_fire":23.49},{"mid_date":"2023-12-27","norm_coh":0.8762,"smoothed":0.6896,"months_post_fire":23.88},{"mid_date":"2024-01-08","norm_coh":0.8486,"smoothed":0.6868,"months_post_fire":24.28},{"mid_date":"2024-01-20","norm_coh":0.2393,"smoothed":0.6331,"months_post_fire":24.67},{"mid_date":"2024-02-01","norm_coh":0.4564,"smoothed":0.7053,"months_post_fire":25.07},{"mid_date":"2024-02-13","norm_coh":0.6838,"smoothed":0.6987,"months_post_fire":25.46},{"mid_date":"2024-02-25","norm_coh":0.3241,"smoothed":0.6125,"months_post_fire":25.85},{"mid_date":"2024-03-08","norm_coh":0.6076,"smoothed":0.6227,"months_post_fire":26.25},{"mid_date":"2024-03-20","norm_coh":1.0393,"smoothed":0.6482,"months_post_fire":26.64},{"mid_date":"2024-04-01","norm_coh":1.0866,"smoothed":0.6505,"months_post_fire":27.04},{"mid_date":"2024-04-13","norm_coh":0.3995,"smoothed":0.6994,"months_post_fire":27.43},{"mid_date":"2024-04-25","norm_coh":0.3162,"smoothed":0.7172,"months_post_fire":27.83},{"mid_date":"2024-05-07","norm_coh":0.8533,"smoothed":0.7991,"months_post_fire":28.22},{"mid_date":"2024-05-19","norm_coh":0.8896,"smoothed":0.843,"months_post_fire":28.61},{"mid_date":"2024-05-31","norm_coh":0.4991,"smoothed":0.8025,"months_post_fire":29.01},{"mid_date":"2024-06-12","norm_coh":0.9942,"smoothed":0.7746,"months_post_fire":29.4},{"mid_date":"2024-06-24","norm_coh":0.8795,"smoothed":0.7617,"months_post_fire":29.8},{"mid_date":"2024-07-06","norm_coh":1.2163,"smoothed":0.805,"months_post_fire":30.19},{"mid_date":"2024-07-18","norm_coh":1.0792,"smoothed":0.8019,"months_post_fire":30.58},{"mid_date":"2024-07-30","norm_coh":0.6666,"smoothed":0.8285,"months_post_fire":30.98},{"mid_date":"2024-08-11","norm_coh":0.2665,"smoothed":0.8895,"months_post_fire":31.37},{"mid_date":"2024-08-23","norm_coh":0.625,"smoothed":0.8804,"months_post_fire":31.77},{"mid_date":"2024-09-04","norm_coh":0.8859,"smoothed":0.947,"months_post_fire":32.16},{"mid_date":"2024-09-16","norm_coh":0.8188,"smoothed":0.9113,"months_post_fire":32.56},{"mid_date":"2024-09-28","norm_coh":1.1828,"smoothed":1.1471,"months_post_fire":32.95},{"mid_date":"2024-10-10","norm_coh":1.2587,"smoothed":1.2,"months_post_fire":33.34},{"mid_date":"2024-10-22","norm_coh":1.2978,"smoothed":1.2242,"months_post_fire":33.74},{"mid_date":"2024-11-03","norm_coh":1.9204,"smoothed":1.4286,"months_post_fire":34.13},{"mid_date":"2024-11-15","norm_coh":1.6996,"smoothed":1.364,"months_post_fire":34.53},{"mid_date":"2024-11-27","norm_coh":1.3219,"smoothed":1.299,"months_post_fire":34.92},{"mid_date":"2024-12-09","norm_coh":0.926,"smoothed":1.2205,"months_post_fire":35.32},{"mid_date":"2024-12-21","norm_coh":0.9557,"smoothed":1.2059,"months_post_fire":35.71},{"mid_date":"2025-01-02","norm_coh":1.4259,"smoothed":1.2839,"months_post_fire":36.1},{"mid_date":"2025-01-14","norm_coh":0.9219,"smoothed":1.1425,"months_post_fire":36.5},{"mid_date":"2025-01-26","norm_coh":1.3483,"smoothed":1.0871,"months_post_fire":36.89},{"mid_date":"2025-02-07","norm_coh":0.9987,"smoothed":1.0434,"months_post_fire":37.29},{"mid_date":"2025-02-19","norm_coh":1.0969,"smoothed":1.0496,"months_post_fire":37.68},{"mid_date":"2025-03-03","norm_coh":0.8033,"smoothed":1.0771,"months_post_fire":38.07},{"mid_date":"2025-03-15","norm_coh":1.0692,"smoothed":1.0578,"months_post_fire":38.47},{"mid_date":"2025-03-27","norm_coh":1.0904,"smoothed":1.0865,"months_post_fire":38.86},{"mid_date":"2025-04-08","norm_coh":0.8413,"smoothed":1.0689,"months_post_fire":39.26},{"mid_date":"2025-04-20","norm_coh":0.9946,"smoothed":1.0801,"months_post_fire":39.65},{"mid_date":"2025-05-02","norm_coh":1.2575,"smoothed":1.078,"months_post_fire":40.05},{"mid_date":"2025-05-14","norm_coh":1.214,"smoothed":1.1027,"months_post_fire":40.44},{"mid_date":"2025-05-26","norm_coh":1.2371,"smoothed":1.1033,"months_post_fire":40.83},{"mid_date":"2025-06-13","norm_coh":1.1555,"smoothed":1.0998,"months_post_fire":41.43},{"mid_date":"2025-07-01","norm_coh":1.121,"smoothed":1.1243,"months_post_fire":42.02},{"mid_date":"2025-07-13","norm_coh":1.0744,"smoothed":1.1346,"months_post_fire":42.41},{"mid_date":"2025-07-25","norm_coh":1.0746,"smoothed":1.1259,"months_post_fire":42.81},{"mid_date":"2025-08-06","norm_coh":1.0764,"smoothed":1.1399,"months_post_fire":43.2},{"mid_date":"2025-08-18","norm_coh":1.0512,"smoothed":1.1413,"months_post_fire":43.59},{"mid_date":"2025-08-30","norm_coh":1.1113,"smoothed":1.147,"months_post_fire":43.99},{"mid_date":"2025-09-11","norm_coh":1.1074,"smoothed":1.1075,"months_post_fire":44.38},{"mid_date":"2025-09-23","norm_coh":1.1615,"smoothed":1.0693,"months_post_fire":44.78},{"mid_date":"2025-10-05","norm_coh":1.3684,"smoothed":1.082,"months_post_fire":45.17},{"mid_date":"2025-10-17","norm_coh":1.2523,"smoothed":1.0858,"months_post_fire":45.57},{"mid_date":"2025-10-29","norm_coh":1.2182,"smoothed":1.0911,"months_post_fire":45.96},{"mid_date":"2025-11-10","norm_coh":0.6869,"smoothed":0.76,"months_post_fire":46.35},{"mid_date":"2025-11-22","norm_coh":0.6542,"smoothed":0.6927,"months_post_fire":46.75},{"mid_date":"2025-12-04","norm_coh":1.2139,"smoothed":1.0777,"months_post_fire":47.14},{"mid_date":"2025-12-16","norm_coh":1.1181,"smoothed":0.9669,"months_post_fire":47.54}]